Metadata-Version: 1.0
Name: basicdistributions
Version: 0.1
Summary: Gaussian and Binomial distributions
Home-page: UNKNOWN
Author: Anudeep Vanjavakam
Author-email: vanjavakamanudeep@gmail.com
License: UNKNOWN
Platform: UNKNOWN
